triplestore/__init__.py
triplestore/store.py
TripleStore-0.1.1.dist-info/LICENSE
TripleStore-0.1.1.dist-info/METADATA
TripleStore-0.1.1.dist-info/WHEEL
TripleStore-0.1.1.dist-info/top_level.txt
TripleStore-0.1.1.dist-info/RECORD
